[{"id":1, "name":"Milton Carlos Katoo", "email":"mckatoo@gmail.com", "username":"mckatoo", "password":"$2y$10$YKaZWZJHq6FpwUOnH5enz..uYJFjazt0O7O01kM3QgTgqo0MjIuDy", "remember_token":"LdUSi9sAawBsuGheVXw5ePlT09Nv1VgE9bKy9EAydDErxE62RcUu7ALGu8a7", "created_at":"2018-08-19 15:29:20", "updated_at":"2018-08-21 04:14:17"},
 {"id":3, "name":"william", "email":"zacariotto@hotmail.com", "username":"william", "password":"$2y$10$Nd56uDm/PavbuPfGPmE1iedQwOvFENmH9/zvOKtcGRfZhp7tDAZyq", "remember_token":"", "created_at":"2018-08-20 12:02:15", "updated_at":"2018-08-20 12:02:15"},
 {"id":4, "name":"Alessandra Maiara Ferreira de Mello", "email":"alessandra.maiara_@hotmail.com", "username":"alessandra", "password":"$2y$10$GBDfijxtV2GHOrFQd01L2uIkERgr67VE/E32niAgFCqvBAymal9OS", "remember_token":"KtnOyeBeLCkZepaBW7o6XVTaKXO7M13itokJPO3qET4CBWykrJPUr0E8dL1F", "created_at":"2018-08-20 12:15:05", "updated_at":"2018-08-20 12:15:05"},
 {"id":5, "name":"DAIANA ALBERTI", "email":"daianaelisaalberti@gmail.com", "username":"daiana", "password":"$2y$10$0y0lFsXPumc2xEXT4EEhg.GTZi.mA1H/11JSJApxhthrgx8DwF.9q", "remember_token":"17Ek5mh2d63S4Lwv2EGmGIAjXlu2N8yF9Fi9mfdREfHPIP166MoN2z1kR7d8", "created_at":"2018-08-20 19:16:18", "updated_at":"2018-08-20 19:16:18"},
 {"id":6, "name":"FILIPE TRANI", "email":"trani.filipe@gmail.com", "username":"felipe", "password":"$2y$10$1HIY8d7zDiALg2yWC45UG.sDNaTQGdOTfpHcx14LEstDc/4tFT/8u", "remember_token":"jxSCtuk6CpHAWBTBJegAyCXmKSDFiDKBQQsHJODcYMHmjWOn3vKhmU3ycmGD", "created_at":"2018-08-20 19:17:04", "updated_at":"2018-08-20 19:17:04"},
 {"id":7, "name":"BRUNA BAUMANN", "email":"bruna.baumann@hotmail.com", "username":"bruna", "password":"$2y$10$d5Cway3yNG499VIHE.H.xuDFOcDUhugF83G9pL2ggLMl2I/wj1DaG", "remember_token":"iHWOwbVI78czkQj7ABzv6ftkG2rLFwxmCwvNoNII6EmIy0Zm3jgNchFImyFT", "created_at":"2018-08-20 19:17:52", "updated_at":"2018-08-20 19:17:52"},
 {"id":8, "name":"DYANA CRISTINA MAGYORI F. SILVA", "email":"dyanamagyori@hotmail.com", "username":"dayana", "password":"$2y$10$YP3GE2zK2p3foTtv3QriueQBlPZo7JVqLPoIdUZAhdoBOfzo4qa1u", "remember_token":"wwf6vjwcYDe1Bq5ZDrIhtDbDBz1o2NdnMmjOaEu6DHXE2DirJB2yaNZU7dtu", "created_at":"2018-08-20 19:47:07", "updated_at":"2018-08-20 19:47:07"},
 {"id":9, "name":"ALESCER DOS SANTOS", "email":"alescer@gmail.com", "username":"alescer", "password":"$2y$10$Gu5TX8KekbkqtGxdEJ16mOQgrtdXvA.ePfarSeseB1IQVuT0QyhMG", "remember_token":"VXReQjdjEgfa30r6vgHKjVfm2lnzLKHsz0FS7CJG2agu6URryHTjvZb5npQT", "created_at":"2018-08-20 19:56:58", "updated_at":"2018-08-20 19:56:58"},
 {"id":10, "name":"CRISTIANE VIT\u00d3RIO", "email":"estagios.iesi@gmail.com", "username":"cris", "password":"$2y$10$8VCUOwNG7mIKat29iW50NOLwWDgkgAeJ4vIVnZqvU8qJL2UBK3Usa", "remember_token":"", "created_at":"2018-08-20 22:53:52", "updated_at":"2018-08-20 22:53:52"}]
